gynumdata/__init__.py
gynumdata/calculate.py
gynumdata-0.0.3.dist-info/LICENSE
gynumdata-0.0.3.dist-info/METADATA
gynumdata-0.0.3.dist-info/WHEEL
gynumdata-0.0.3.dist-info/top_level.txt
gynumdata-0.0.3.dist-info/RECORD
