Metadata-Version: 2.1
Name: gynumdata
Version: 0.0.3
Summary: A simple package calculating values for a single number and created in my Udemy course
Home-page: https://github.com/yawbrother/python-pkgdev
Author: Yaw Brother
Author-email: gsolomonsa@gmail.com
License: UNKNOWN
Keywords: package numbers calculations
Platform: UNKNOWN
Classifier: License :: OSI Approved :: MIT License
Classifier: Programming Language :: Python :: 3
Classifier: Operating System :: OS Independent
